llama_index/embeddings/text_embeddings_inference/__init__.py
llama_index/embeddings/text_embeddings_inference/base.py
llama_index_embeddings_text_embeddings_inference-0.4.2.dist-info/METADATA
llama_index_embeddings_text_embeddings_inference-0.4.2.dist-info/WHEEL
llama_index_embeddings_text_embeddings_inference-0.4.2.dist-info/licenses/LICENSE
llama_index_embeddings_text_embeddings_inference-0.4.2.dist-info/RECORD
