Metadata-Version: 2.4
Name: llama-index-embeddings-text-embeddings-inference
Version: 0.4.2
Summary: llama-index embeddings text embeddings inference integration
Author-email: Your Name <you@example.com>
License-Expression: MIT
License-File: LICENSE
Requires-Python: <4.0,>=3.9
Requires-Dist: httpx>=0.26.0
Requires-Dist: llama-index-core<0.15,>=0.13.0
Requires-Dist: llama-index-utils-huggingface<0.5,>=0.4.0
